Metadata-Version: 2.4
Name: llama-index-vector-stores-analyticdb
Version: 0.4.1
Summary: llama-index vector_stores analyticdb integration
Author-email: JingYi <yangshangpo.ysp@alibaba-inc.com>
License-Expression: MIT
License-File: LICENSE
Requires-Python: <4.0,>=3.9
Requires-Dist: alibabacloud-gpdb20160503<4,>=3.5.0
Requires-Dist: alibabacloud-tea-openapi<0.4,>=0.3.8
Requires-Dist: llama-index-core<0.15,>=0.13.0
